{
  "main": {
    "id": "158874cebada007e",
    "type": "split",
    "children": [
      {
        "id": "52be7317b09ba1c7",
        "type": "tabs",
        "children": [
          {
            "id": "1eedd022175503ec",
            "type": "leaf",
            "state": {
              "type": "markdown",
              "state": {
                "file": "src/other/design_pattern/creational/creational_pattern_main.md",
                "mode": "source",
                "source": false
              },
              "icon": "lucide-file",
              "title": "creational_pattern_main"
            }
          },
          {
            "id": "63ec6fd7bd022a01",
            "type": "leaf",
            "state": {
              "type": "markdown",
              "state": {
                "file": "src/backend/python/python_main.md",
                "mode": "source",
                "source": false
              },
              "icon": "lucide-file",
              "title": "python_main"
            }
          }
        ]
      }
    ],
    "direction": "vertical"
  },
  "left": {
    "id": "8d2385bf6dc5e0a5",
    "type": "split",
    "children": [
      {
        "id": "25246680da638d1d",
        "type": "tabs",
        "children": [
          {
            "id": "4b945fd0a43c579c",
            "type": "leaf",
            "state": {
              "type": "file-explorer",
              "state": {
                "sortOrder": "alphabetical",
                "autoReveal": false
              },
              "icon": "lucide-folder-closed",
              "title": "Files"
            }
          },
          {
            "id": "cf19065c94e5d17c",
            "type": "leaf",
            "state": {
              "type": "search",
              "state": {
                "query": "",
                "matchingCase": false,
                "explainSearch": false,
                "collapseAll": false,
                "extraContext": false,
                "sortOrder": "alphabetical"
              },
              "icon": "lucide-search",
              "title": "Search"
            }
          },
          {
            "id": "2c79edf21f9aacc1",
            "type": "leaf",
            "state": {
              "type": "bookmarks",
              "state": {},
              "icon": "lucide-bookmark",
              "title": "Bookmarks"
            }
          }
        ]
      }
    ],
    "direction": "horizontal",
    "width": 300
  },
  "right": {
    "id": "b3f7e1edd8e1d797",
    "type": "split",
    "children": [
      {
        "id": "8e4088f72c395984",
        "type": "tabs",
        "children": [
          {
            "id": "d7791ebfdc976e9e",
            "type": "leaf",
            "state": {
              "type": "backlink",
              "state": {
                "file": "src/diagramme/db_diagramme/er_modell.md",
                "collapseAll": false,
                "extraContext": false,
                "sortOrder": "alphabetical",
                "showSearch": false,
                "searchQuery": "",
                "backlinkCollapsed": false,
                "unlinkedCollapsed": true
              },
              "icon": "links-coming-in",
              "title": "Backlinks for er_modell"
            }
          },
          {
            "id": "29f109b94f80f4ae",
            "type": "leaf",
            "state": {
              "type": "outgoing-link",
              "state": {
                "file": "src/diagramme/db_diagramme/er_modell.md",
                "linksCollapsed": false,
                "unlinkedCollapsed": true
              },
              "icon": "links-going-out",
              "title": "Outgoing links from er_modell"
            }
          },
          {
            "id": "0a0f7300cbcdc552",
            "type": "leaf",
            "state": {
              "type": "tag",
              "state": {
                "sortOrder": "frequency",
                "useHierarchy": true,
                "showSearch": false,
                "searchQuery": ""
              },
              "icon": "lucide-tags",
              "title": "Tags"
            }
          },
          {
            "id": "8294b495d9d9dced",
            "type": "leaf",
            "state": {
              "type": "outline",
              "state": {
                "file": "src/diagramme/db_diagramme/er_modell.md",
                "followCursor": false,
                "showSearch": false,
                "searchQuery": ""
              },
              "icon": "lucide-list",
              "title": "Outline of er_modell"
            }
          }
        ]
      }
    ],
    "direction": "horizontal",
    "width": 300,
    "collapsed": true
  },
  "left-ribbon": {
    "hiddenItems": {
      "switcher:Open quick switcher": false,
      "graph:Open graph view": false,
      "canvas:Create new canvas": false,
      "daily-notes:Open today's daily note": false,
      "templates:Insert template": false,
      "command-palette:Open command palette": false
    }
  },
  "active": "1eedd022175503ec",
  "lastOpenFiles": [
    "src/other/design_pattern/creational/factory.md",
    "src/other/design_pattern/other/mvc.md",
    "src/other/design_pattern/design_pattern_main.md",
    "src/other/design_pattern/structural/decorator.md",
    "src/other/design_pattern/creational/creational_pattern_main.md",
    "Pasted image 20250505020724.png",
    "src/other/architecture/api/api_main.md",
    "src/other/architecture/api/http_status_codes.md",
    "src/other/architecture/api/soap.md",
    "src/other/architecture/api/rest.md",
    "src/other/architecture/architecture_main.md",
    "src/database/other/data/json.md",
    "src/database/other/data/data_format.md",
    "src/database/other/data",
    "src/database/relational/sql.md",
    "src/other/design_pattern/behavioral/observer.md",
    "src/other/architecture/api",
    "images/BigPicture-AP2-FIAE.pdf",
    "src/database/relational/My_SQL.md",
    "src/database/relational/relational_database_main.md",
    "src/database/database_main.md",
    "knowledge_main.md",
    "src/other/other_main.md",
    "images/bubblesort_ad.png",
    "src/other/algorithms/algorithms_main.md",
    "src/backend/python/python_main.md",
    "images/Pasted image 20250504153832.png",
    "src/other/algorithms/sort_algorithms/sort_algorithms_main.md",
    "src/other/algorithms/sort_algorithms/bubble_sort.md",
    "src/other/algorithms/search_algorithms/binary_search.md",
    "src/other/algorithms/search_algorithms/search_algorithms_main.md",
    "src/other/algorithms/search_algorithms/linear_search.md",
    "Pasted image 20250504160009.png",
    "images/Pasted image 20250504152620.png",
    "images/Pasted image 20250504152214.png",
    "images/diagrams/relationales_datenbankmodell_cheatsheet.svg",
    "images/diagrams/ER_Modell_Cheatsheet.svg",
    "images/Pasted image 20250503043757.png",
    "images/Pasted image 20250503043401.png",
    "images/cheatsheet_class_diagram.pdf",
    "images/cheatsheet_class_diagram 1.pdf",
    "src/other/runtimes",
    "src/other/other",
    "src/other/algorithms/sort_algorithms",
    "src/other/algorithms/search_algorithms",
    "src/other/design_pattern/other",
    "Untitled.canvas"
  ]
}